<annotation>
	<folder>totrain</folder>
	<filename>COCO_train2014_000000001507.jpg</filename>
	<path>C:\Users\User\Desktop\objectDetection\totrain\COCO_train2014_000000001507.jpg</path>
	<source>
		<database>Unknown</database>
	</source>
	<size>
		<width>612</width>
		<height>612</height>
		<depth>3</depth>
	</size>
	<segmented>0</segmented>
	<object>
		<name>soup</name>
		<pose>Unspecified</pose>
		<truncated>0</truncated>
		<difficult>0</difficult>
		<bndbox>
			<xmin>8</xmin>
			<ymin>60</ymin>
			<xmax>303</xmax>
			<ymax>298</ymax>
		</bndbox>
	</object>
	<object>
		<name>spool</name>
		<pose>Unspecified</pose>
		<truncated>0</truncated>
		<difficult>0</difficult>
		<bndbox>
			<xmin>33</xmin>
			<ymin>402</ymin>
			<xmax>241</xmax>
			<ymax>588</ymax>
		</bndbox>
	</object>
</annotation>
